README
pyb-init
setup.py
pyb_init/__init__.py
pyb_init/configuration.py
pyb_init/reactor.py
pyb_init/tasks.py
pyb_init/vcs_tools.py
pyb_init.egg-info/PKG-INFO
pyb_init.egg-info/SOURCES.txt
pyb_init.egg-info/dependency_links.txt
pyb_init.egg-info/requires.txt
pyb_init.egg-info/top_level.txt
pyb_init.egg-info/zip-safe