Metadata-Version: 1.1
Name: pyb-init
Version: 0.1.18
Summary: pybuilder project initialization
Home-page: https://github.com/mriehl/pyb_init
Author: Maximilien Riehl
Author-email: maximilien.riehl@gmail.com
License: WTFPL
Platform: UNKNOWN
Classifier: Development Status :: 4 - Beta
Classifier: Intended Audience :: Developers
Classifier: License :: Freely Distributable
Classifier: Programming Language :: Python
Classifier: Natural Language :: English
Classifier: Operating System :: Unix
Classifier: Topic :: Software Development :: Build Tools
